certbot_dns_firstdomains/__init__.py
certbot_dns_firstdomains/dns_firstdomains.py
certbot_dns_firstdomains-1.0.dist-info/LICENSE.txt
certbot_dns_firstdomains-1.0.dist-info/METADATA
certbot_dns_firstdomains-1.0.dist-info/WHEEL
certbot_dns_firstdomains-1.0.dist-info/entry_points.txt
certbot_dns_firstdomains-1.0.dist-info/top_level.txt
certbot_dns_firstdomains-1.0.dist-info/RECORD
